rica/__init__.py
rica/exceptions.py
rica/adapters/__init__.py
rica/adapters/base.py
rica/adapters/transformers_adapter.py
rica/core/__init__.py
rica/core/application.py
rica/utils/__init__.py
rica/utils/prompt.py
rica/utils/validation.py
rica_server-0.0.1.dev2.dist-info/licenses/LICENSE
rica_server-0.0.1.dev2.dist-info/METADATA
rica_server-0.0.1.dev2.dist-info/WHEEL
rica_server-0.0.1.dev2.dist-info/top_level.txt
rica_server-0.0.1.dev2.dist-info/RECORD
