Metadata-Version: 2.4
Name: rica-server
Version: 0.0.1.dev2
Summary: Multi-threaded Reasoning for Large Language Models
Author-email: kaokao221 <kaokao221@outlook.com>
License-Expression: GPL-3.0-only
Project-URL: Repository, https://github.com/rica-team/rica-server.git
Keywords: llms,pytorch,nlp
Requires-Python: >=3.12
License-File: LICENSE
Requires-Dist: jinja2
Requires-Dist: jsonschema
Provides-Extra: pt
Requires-Dist: transformers; extra == "pt"
Requires-Dist: torch; extra == "pt"
Requires-Dist: timm; extra == "pt"
Requires-Dist: accelerate; extra == "pt"
Requires-Dist: hf_xet; extra == "pt"
Provides-Extra: dev
Requires-Dist: pytest; extra == "dev"
Dynamic: license-file
